<annotation>
	<folder>Wouter</folder>
	<filename>20190516_095911.jpg</filename>
	<path>C:\Projects\robotica5\training\img\Egg\Wouter\20190516_095911.jpg</path>
	<source>
		<database>Unknown</database>
	</source>
	<size>
		<width>720</width>
		<height>405</height>
		<depth>3</depth>
	</size>
	<segmented>0</segmented>
	<object>
		<name>fakeEgg</name>
		<pose>Unspecified</pose>
		<truncated>0</truncated>
		<difficult>0</difficult>
		<bndbox>
			<xmin>382</xmin>
			<ymin>159</ymin>
			<xmax>440</xmax>
			<ymax>229</ymax>
		</bndbox>
	</object>
</annotation>
